swashes/__init__.py
swashes/__main__.py
swashes/data/bin/swashes
swashes-1.5.0.dist-info/RECORD
swashes-1.5.0.dist-info/WHEEL
swashes-1.5.0.dist-info/entry_points.txt
swashes-1.5.0.dist-info/METADATA
