Metadata-Version: 2.2
Name: swashes
Version: 1.5.0
Summary: A Python package for the SWASHES executable.
Author-Email: Laurent Courty <lrntct@gmail.com>
License: CECILL-2.0
Classifier: Development Status :: 5 - Production/Stable
Classifier: Intended Audience :: Science/Research
Classifier: Programming Language :: C++
Classifier: Operating System :: OS Independent
Classifier: Topic :: Scientific/Engineering
Classifier: Topic :: Scientific/Engineering :: Hydrology
Project-URL: Homepage, https://www.idpoisson.fr/swashes/
Project-URL: Repository, https://github.com/lrntct/swashes-python
Requires-Python: >=3.10
